PQRLab/__init__.py
PQRLab/pqrcore/__init__.py
PQRLab/pqrcore/expression.py
PQRLab/pqrcore/devices/__init__.py
PQRLab/pqrcore/devices/device.py
PQRLab/pqrcore/devices/generators/__init__.py
PQRLab/pqrcore/devices/generators/generator.py
PQRLab/pqrcore/experiment/__init__.py
PQRLab/pqrcore/experiment/signal.py
PQRLab/pqrspincore/DecodeSignal.py
PQRLab/pqrspincore/__init__.py
PQRLab/pqrspincore/read_pb_file.py
PQRLab/pqrspincore/spinapi.py
PQRLab/pqrspincore/spincore_data_trans.py
PQRLab/pqrspincore/utf8 convert.py
PQRLab-0.4.0.dist-info/LICENSE
PQRLab-0.4.0.dist-info/METADATA
PQRLab-0.4.0.dist-info/WHEEL
PQRLab-0.4.0.dist-info/top_level.txt
PQRLab-0.4.0.dist-info/RECORD
