Metadata-Version: 2.1
Name: PQRLab
Version: 0.4.0
Summary: Controll System for PQR.
Home-page: https://gitee.com/teshenghsiang/PQRLab
Author: PQR Team
Author-email: carrollxiang@gmail.com
License: UNKNOWN
Platform: UNKNOWN
Classifier: Programming Language :: Python :: 3
Classifier: License :: OSI Approved :: MIT License
Classifier: Operating System :: OS Independent
